{"0": {"type": "tweet", "origin": "256224314821582848", "tweets": ["256224314821582848"], "description": "#US Deploying Military Personnel to #Syria, #Jordan Border - See on Scoop.it - From Tahrir Square RT MORE:... "}, "1": {"type": "website", "origin": "http://benperrusi-blog.tumblr.com/post/33342636308#_=_", "tweets": ["256224314821582848"], "description": "#US Deploying Military Personnel to #Syria, #Jordan Border - See on Scoop.it - From Tahrir Square RT MORE:...  See on Scoop.it - From Tahrir Square\nRT\nMORE:\nhttp://rickrozoff.wordpress.com/2012/10/11/nato-headquarters-pentagon-conspiring-with-jordan-turkey-against-syria/\nJORDAN..."}, "2": {"type": "tweet", "origin": "256237812133814272", "tweets": ["256237812133814272"], "description": "#Iraq, #Russia Oppose Foreign Interference In #Syria, Middle\u00a0East - See on Scoop.it - From Tahrir Square... "}, "3": {"type": "website", "origin": "http://benperrusi-blog.tumblr.com/post/33346008555#_=_", "tweets": ["256237812133814272"], "description": "#Iraq, #Russia Oppose Foreign Interference In #Syria, Middle\u00a0East - See on Scoop.it - From Tahrir Square...  See on Scoop.it - From Tahrir Square\nSTOP NATO\nMORE:\n(1) http://rt.com/news/iraqi-turkey-syria-nato-100/\n(2)..."}, "4": {"type": "tweet", "origin": "256312969661665281", "tweets": ["256312969661665281"], "description": "I think @fhienyx would love to be where I am right now #Tahrir #graffiti #art #picstitch   @ Tahrir Square "}, "5": {"type": "website", "origin": "https://www.instagram.com/p/QorPy2jiFl/", "tweets": ["256312969661665281"], "description": "I think @fhienyx would love to be where I am right now #Tahrir #graffiti #art #picstitch   @ Tahrir Square  13 Likes, 2 Comments - Nadia Abdelsalam (@nadiabdelsalam) on Instagram: \u201cI think @fhienyx would love to be where I am right now #Tahrir #graffiti #art #picstitch\u201d"}, "6": {"type": "tweet", "origin": "256424672638423040", "tweets": ["256424672638423040"], "description": "The Arab Spring Spreading to Jordan | Gerard Direct: We saw this in Tahrir Square in Cairo, and we can ...  #asematy"}, "7": {"type": "website", "origin": "http://gerarddirect.com/2012/10/11/the-arab-spring-spreading-to-jordan/", "tweets": ["256424672638423040"], "description": "The Arab Spring Spreading to Jordan | Gerard Direct: We saw this in Tahrir Square in Cairo, and we can ...  #asematy The \u201cArab Spring\u201d Spreading to Jordan | Gerard Direct"}, "8": {"type": "tweet", "origin": "256466128799399936", "tweets": ["256466128799399936"], "description": "Egyptian president sacks prosecutor general: Egyptian President Mohamed Morsi sacked Thursday prosecutor general... "}, "9": {"type": "news", "origin": "http://www.bignewsnetwork.com/article/209968313/egyptian-president-sacks-prosecutor-general", "tweets": ["256466128799399936"], "description": "Egyptian president sacks prosecutor general: Egyptian President Mohamed Morsi sacked Thursday prosecutor general...  Egyptian president sacks prosecutor general"}, "10": {"type": "tweet", "origin": "256478015612129280", "tweets": ["256478015612129280"], "description": "Clashed in #Tahrir between supporters &amp; opponents of #Morsi #Cairo #Egypt"}, "11": {"type": "tweet", "origin": "256489902324207618", "tweets": ["256489902324207618"], "description": "Tahrir Square-gang raped CBS journalist Lara Logan has lost her naivete about Islam (Dennis Prager)  via @youtube"}, "12": {"type": "video", "origin": "https://www.youtube.com/watch?v=N3fVvWnge_Y&sns=tw", "tweets": ["256489902324207618"], "description": "Tahrir Square-gang raped CBS journalist Lara Logan has lost her naivete about Islam (Dennis Prager)  via @youtube From \"The Dennis Prager Show\" (Wednesday, October 11, 2012 edition)"}, "13": {"type": "tweet", "origin": "256573574599561217", "tweets": ["256573574599561217"], "description": "These people are much more craycray and rude then the president and his opponent"}, "14": {"type": "tweet", "origin": "256580096389939200", "tweets": ["256580096389939200"], "description": "#US &amp; WW3: Romney sings Da Doo War War - See on Scoop.it - From Tahrir Square Asia Times Online -\u00a0By Pepe... "}, "15": {"type": "website", "origin": "http://benperrusi-blog.tumblr.com/post/33405442780#_=_", "tweets": ["256580096389939200"], "description": "#US &amp; WW3: Romney sings Da Doo War War - See on Scoop.it - From Tahrir Square Asia Times Online -\u00a0By Pepe...  See on Scoop.it - From Tahrir Square\nAsia Times Online - By Pepe Escobar\nUS ON MENA:\nhttp://www.scoop.it/t/from-tahrir-square?q=US\nSee on atimes.com"}, "16": {"type": "tweet", "origin": "256680868834324480", "tweets": ["256680868834324480"], "description": "Martyr:  Abdo Saber Abdo Age 24 Died in  Tahrir Square by  Gunshot in the head and brain laceration ..., Garage worker #Egypt #jan25"}, "17": {"type": "tweet", "origin": "256708698032984064", "tweets": ["256708698032984064"], "description": "Brothers gangs prevent popular trend speakers from ascending #tahrir podium leading to clashes\n\nvia@Tahrir_News #Egypt#Morsi#MB democracy"}, "18": {"type": "tweet", "origin": "256709603922956288", "tweets": ["256709603922956288"], "description": "clashes between Mursi supporters &amp;opponents Mohamed Mahmoud Street #tahrir via @Tahrir_News #Egypt"}, "19": {"type": "tweet", "origin": "256710581162233857", "tweets": ["256710581162233857"], "description": "#Egypt #Jan25 Protests begin against Battle of the Camel ruling, constitution, Morsy and more  #tahrir"}, "20": {"type": "tweet", "origin": "256712833629306881", "tweets": ["256712833629306881"], "description": "#Egypt #Masr Tahrir Square quiet ahead of protests  #Jan25"}, "21": {"type": "tweet", "origin": "256718500075298816", "tweets": ["256718500075298816"], "description": "#Egypt #Jan25 Tahrir Square quiet ahead of protests  #tahrir"}, "22": {"type": "tweet", "origin": "256721943842148353", "tweets": ["256721943842148353"], "description": "#Morsy peeps: \"the people support the president's decision\" #mb #Tahrir"}, "23": {"type": "tweet", "origin": "256723269166710784", "tweets": ["256723269166710784"], "description": "Scuffles between Mursi supporters, opponents in Tahrir - News - Aswat Masriya  #Egypt"}, "24": {"type": "news", "origin": "http://en.aswatmasriya.com/news/details/11012", "tweets": ["256723269166710784"], "description": "Scuffles between Mursi supporters, opponents in Tahrir - News - Aswat Masriya  #Egypt Scuffles erupted in Tahrir square between supporters and opponents of President Mohamed Mursi on the \u201cFriday of Accountability\u201d, Nile TV correspondent reported on Friday."}, "25": {"type": "tweet", "origin": "256726083473395713", "tweets": ["256726083473395713"], "description": "Anti #Morsy crowd pushed all the way back to #AUC library. #Tahrir"}, "26": {"type": "tweet", "origin": "256730164636028928", "tweets": ["256730164636028928"], "description": "what exactly sparked the clashes? #Tahrir"}, "27": {"type": "tweet", "origin": "256735239857139712", "tweets": ["256735239857139712"], "description": "UPDATE 2: Pro-Brotherhood protesters attack rival's stage in Tahrir Square  #Egypt"}, "28": {"type": "website", "origin": "http://english.ahram.org.eg/NewsContent/1/64/55417/Egypt/Politics-/UPDATE--ProBrotherhood-protesters-attack-rivals-st.aspx", "tweets": ["256735239857139712"], "description": "UPDATE 2: Pro-Brotherhood protesters attack rival's stage in Tahrir Square  #Egypt \r\n\tPro-Brotherhood demonstrators attack 'Accountability Friday' protest in Tahrir - Politics  - Egypt - Ahram Online \r\n"}, "29": {"type": "tweet", "origin": "256740323299061761", "tweets": ["256740323299061761"], "description": "After the clashes in #Tahrir , the chants now in all the marches are against #MB, #Morsi and #Badei"}, "30": {"type": "tweet", "origin": "256742370140364800", "tweets": ["256742370140364800"], "description": "Minor clashes between rival supporters in Giza Square and Tahrir Square. #Egypt"}, "31": {"type": "tweet", "origin": "256750838129762305", "tweets": ["256750838129762305"], "description": "#Egypt #Jan25 Update: Clashes renew in Tahrir between activists, Brotherhood  #tahrir"}, "32": {"type": "website", "origin": "http://rssmasr.com/en/2012/10/12/update-clashes-renew-in-tahrir-between-activists-brotherhood/", "tweets": ["256750838129762305"], "description": "#Egypt #Jan25 Update: Clashes renew in Tahrir between activists, Brotherhood  #tahrir rssmasr.com"}, "33": {"type": "tweet", "origin": "256751425537839104", "tweets": ["256751425537839104"], "description": "Fight breaking out between anti and pro #Morsy protesters. Rock throwing. #Tahrir @DailyNewsEgypt"}, "34": {"type": "tweet", "origin": "256752801374425088", "tweets": ["256752801374425088"], "description": "#Egypt #Masr Update: Clashes renew in Tahrir between activists, Brotherhood; More marches head towards square  #Jan25"}, "35": {"type": "tweet", "origin": "256752805610668033", "tweets": ["256752805610668033"], "description": "Egypt's President Morsi removes state prosecutor seen as Mubarak loyalist "}, "36": {"type": "website", "origin": "https://feedly.com/", "tweets": ["256752805610668033"], "description": "Egypt's President Morsi removes state prosecutor seen as Mubarak loyalist  Feedly connects you to the information and knowledge you care about. We help you get more out of you work, education, hobbies and interests. The feedly platform lets you discover sources of quality content, follow and read everything those sources publish with ease and organize everything in one place."}, "37": {"type": "tweet", "origin": "256754000936976384", "tweets": ["256754000936976384"], "description": "It seems like the ultras just arrived to the square. People are cheering for them #Tahrir"}, "38": {"type": "tweet", "origin": "256756957757718528", "tweets": ["256756957757718528"], "description": "Some kind of home-made bombs just went off in Mohamed Mahmoud St. #Tahrir"}, "39": {"type": "tweet", "origin": "256757024732348417", "tweets": ["256757024732348417"], "description": "the most intersting thing today is the coverage of the egyptian t.V to tahrir square...... fein ayamk ya anas (al fekky)"}, "40": {"type": "tweet", "origin": "256760208179736576", "tweets": ["256760208179736576"], "description": "Update: Protester injured in Tahrir clashes: Several protests with different aims are occupying the square today... "}, "41": {"type": "news", "origin": "http://www.egyptindependent.com//news/update-microbuses-set-ablaze-near-tahrir-brotherhood-members-chased-square", "tweets": ["256760208179736576"], "description": "Update: Protester injured in Tahrir clashes: Several protests with different aims are occupying the square today...  An anti-Brotherhood vibe prevailed in Tahrir Square on Friday evening, following clashes between members of the group and other protesters throughout the day. Protesters in the square appear to have driven out the Muslim Brotherhood youth with whom they had been fighting throughout the day, eyewitnesses reported."}, "42": {"type": "tweet", "origin": "256761089059082241", "tweets": ["256761089059082241"], "description": "Both Sides in #Tahrir Square are tryin to win for their point of view..well congratulations you're both wrong :S"}, "43": {"type": "tweet", "origin": "256761131220221952", "tweets": ["256761131220221952"], "description": "The fighting is still on going in Mohamed Mahmoud. I'm stuck here but I think there's clashes elsewhere too. #Tahrir"}, "44": {"type": "tweet", "origin": "256762909529608193", "tweets": ["256762909529608193"], "description": "BREAKING: Clashes erupt on Egypt\u2019s #Tahrir Square, at least 10 injured "}, "45": {"type": "news", "origin": "https://www.rt.com/news/clashes-egypt-tahrir-square-287/", "tweets": ["256762909529608193", "256768479678562304", "256771054964457472", "256994695140478978"], "description": "BREAKING: Clashes erupt on Egypt\u2019s #Tahrir Square, at least 10 injured  Thousands of supporters and opponents of Egyptian President Mohamed Morsi battled for control of Cairo\u2019s Tahrir Square, the epicenter of the recent revolution. Over one hundred protesters are reported injured in the violence. Clashes erupt on Egypt\u2019s Tahrir Square, at least 10 injured  Clashes erupt on Egypt's Tahrir Square, at least 10 injured - RT (blog): RT (blog)Clashes erupt on ...  #ifollowback Clashes erupt on Egypt\u2019s Tahrir Square, over 100 injured "}, "46": {"type": "tweet", "origin": "256763530450182144", "tweets": ["256763530450182144"], "description": "Clashes on Talaat harb st &amp;Mohamed Mahmoud. Everyone saying ' this is ridiculous, why are we fighting?' Also 'who's fighting' #tahrir"}, "47": {"type": "tweet", "origin": "256763828262535168", "tweets": ["256763828262535168"], "description": "Then who's chanting Morsi Morsi? MT @Ikhwanweb: MuslimBrotherhood: we are not involved in Tahrir clashes, and none of our members were there"}, "48": {"type": "tweet", "origin": "256765807844003842", "tweets": ["256765807844003842"], "description": "Clashes in #Tahrir square, #Cairo continue&amp;stones now are coupled with Molotov Cocktails exchanged between Brotherhood&amp;their opponents #Egyp"}, "49": {"type": "tweet", "origin": "256767242212081664", "tweets": ["256767242212081664"], "description": "Morsi Supporters and Opponents Clash in Egypt's Tahrir Square - Afp "}, "50": {"type": "website", "origin": "http://www.mt5.com/forex_news/quickview/1314630/", "tweets": ["256767242212081664"], "description": "Morsi Supporters and Opponents Clash in Egypt's Tahrir Square - Afp  The latest news on the current events in the world of economy and finance. Recent Forex analysis and online forecasts for prices of financial instruments."}, "51": {"type": "tweet", "origin": "256768479678562304", "tweets": ["256768479678562304"], "description": "Clashes erupt on Egypt\u2019s Tahrir Square, at least 10 injured "}, "52": {"type": "tweet", "origin": "256768769022627842", "tweets": ["256768769022627842"], "description": "Egypt's Morsi vows justice after prosecutor flap: CAIRO AFP - Egypts President Mohamed Morsi pledged on Friday t... "}, "53": {"type": "news", "origin": "https://www.modernghana.com/news/423562/1/egypts-morsi-vows-justice-after-prosecutor-flap.html", "tweets": ["256768769022627842"], "description": "Egypt's Morsi vows justice after prosecutor flap: CAIRO AFP - Egypts President Mohamed Morsi pledged on Friday t...  CAIRO (AFP) - Egypt's President Mohamed Morsi pledged on Friday to bring to justice Mubarak-era officials, a day after his bid to sack the top prosecutor infuri "}, "54": {"type": "tweet", "origin": "256771054964457472", "tweets": ["256771054964457472"], "description": "Clashes erupt on Egypt's Tahrir Square, at least 10 injured - RT (blog): RT (blog)Clashes erupt on ...  #ifollowback"}, "55": {"type": "tweet", "origin": "256771360834072577", "tweets": ["256771360834072577"], "description": "Clashes in Tahrir.."}, "56": {"type": "tweet", "origin": "256772401373782016", "tweets": ["256772401373782016"], "description": "Clashes at every street around Tahrir over the course of the day. #camelbattle #tahrir #morsi #egypt"}, "57": {"type": "tweet", "origin": "256776515671429120", "tweets": ["256776515671429120"], "description": "#Egypt #Jan25 Update: More protesters injured as fighting intensifies in Tahrir  #masr"}, "58": {"type": "tweet", "origin": "256776532406714368", "tweets": ["256776532406714368"], "description": "#Egypt #Masr BREAKING: Pellets, Molotovs used as Tahrir clashes escalate  #Sinai"}, "59": {"type": "tweet", "origin": "256779476912975873", "tweets": ["256779476912975873"], "description": "BRB Tahrir Square"}, "60": {"type": "tweet", "origin": "256780638944890880", "tweets": ["256780638944890880"], "description": "Smoke in Mohamed Mahmoud and big clash between the #MB and other demonstrates #Tahrir #Egypt"}, "61": {"type": "tweet", "origin": "256784782632046592", "tweets": ["256784782632046592"], "description": "Muslim Brotherhood members not responsible for ongoing clashes in Cairo's #Tahrir Square, says Mahmoud Ghozlan  #Egypt"}, "62": {"type": "website", "origin": "http://english.ahram.org.eg/NewsContent/1/64/55444/Egypt/Politics-/Brotherhood-not-responsible-for-Tahrir-clashes-Spo.aspx", "tweets": ["256784782632046592"], "description": "Muslim Brotherhood members not responsible for ongoing clashes in Cairo's #Tahrir Square, says Mahmoud Ghozlan  #Egypt \r\n\t'Brotherhood not responsible for Tahrir clashes': Spokesperson - Politics  - Egypt - Ahram Online \r\n"}, "63": {"type": "tweet", "origin": "256786397795598336", "tweets": ["256786397795598336"], "description": "#TeamFollowBack CAIRO (Reuters) - Opponents and supporters of Egypt's President Mohamed Mur...  #Follow @Kaijzer #FF"}, "64": {"type": "news", "origin": "http://www.reuters.com/article/us-egypt-protest-idUSBRE89B0YC20121012", "tweets": ["256786397795598336"], "description": "#TeamFollowBack CAIRO (Reuters) - Opponents and supporters of Egypt's President Mohamed Mur...  #Follow @Kaijzer #FF Opponents and supporters of Egyptian President Mohamed Mursi clashed in Cairo on Friday in the first street violence between rival factions since the Islamist leader took office."}, "65": {"type": "tweet", "origin": "256788339628314624", "tweets": ["256788339628314624"], "description": "News:  Egypt: Scuffles Between Mursi Supporters, Opponents in Tahrir "}, "66": {"type": "website", "origin": "http://humanitariannews.org/20121012/egypt-scuffles-between-mursi-supporters-opponents-tahrir", "tweets": ["256788339628314624"], "description": "News:  Egypt: Scuffles Between Mursi Supporters, Opponents in Tahrir  [Aswat Masriya]Scuffles erupted in Tahrir square between supporters and opponents of President Mohamed Mursi on the \"Friday of Accountability\", Nile TV correspondent reported on Friday."}, "67": {"type": "tweet", "origin": "256788465532956673", "tweets": ["256788465532956673"], "description": "Clashes in #Tahrir Square \nWhy can't #Egypt and the #Arab world be more united. Always fights"}, "68": {"type": "video", "origin": "https://www.youtube.com/watch?v=MUjTDUhY6qY&feature=plcp", "tweets": ["256788465532956673"], "description": "Clashes in #Tahrir Square \nWhy can't #Egypt and the #Arab world be more united. Always fights Subscribe to our channel http://bit.ly/AJSubscribe Al Jazeera's Sherine Tadros reports."}, "69": {"type": "tweet", "origin": "256789828547522560", "tweets": ["256789828547522560"], "description": "BREAKING: 41 people injured as pro and anti-#Morsi protesters engage in a stand-off in #Tahrir, #Egypt. Rockets/ Molotovs fired."}, "70": {"type": "tweet", "origin": "256795881033060352", "tweets": ["256795881033060352"], "description": "mohamed batagy calls all brotherhood members get out from tahrir  by safety way"}, "71": {"type": "tweet", "origin": "256802176368799746", "tweets": ["256802176368799746"], "description": "Egypt tensions spark clashes in Cairo's Tahrir Square - BBC News "}, "72": {"type": "news", "origin": "http://www.bbc.co.uk/news/world-middle-east-19928452", "tweets": ["256802176368799746", "256802176544940032"], "description": "Egypt tensions spark clashes in Cairo's Tahrir Square - BBC News  Fresh clashes break out in the Egyptian capital Cairo in the worst violence since President Mohammed Mursi took office at the end of June. Egypt tensions spark clashes in Cairo's Tahrir Square - BBC News "}, "73": {"type": "tweet", "origin": "256802176544940032", "tweets": ["256802176544940032"], "description": "Egypt tensions spark clashes in Cairo's Tahrir Square - BBC News "}, "74": {"type": "tweet", "origin": "256803770502090752", "tweets": ["256803770502090752"], "description": "I can't even look at tahrir square the way it is know. But the fascinating old scene will emerge back some day.  #tahrir #jan25"}, "75": {"type": "tweet", "origin": "256805825492951040", "tweets": ["256805825492951040"], "description": "#Liberals, #Islamists clash in #Cairo Protest against #Morsi: \"Islamists prevented us...now controlling the square\"  "}, "76": {"type": "news", "origin": "http://www.ynetnews.com/articles/0,7340,L-4291414,00.html", "tweets": ["256805825492951040"], "description": "#Liberals, #Islamists clash in #Cairo Protest against #Morsi: \"Islamists prevented us...now controlling the square\"   More than 100 people injured as members of rival factions throw stones, bottles and petrol bombs, some fighting hand-to-hand"}, "77": {"type": "tweet", "origin": "256807045955743748", "tweets": ["256807045955743748"], "description": "Hundreds hospitalised in Tahrir (Cairo\\ Egypt) clashes"}, "78": {"type": "tweet", "origin": "256809072089759745", "tweets": ["256809072089759745"], "description": "Backers, critics of Egypt president clash in Cairo: Thousands of supporters and opponents of Egypt's new Islamis... "}, "79": {"type": "website", "origin": "http://adf.ly/suspended", "tweets": ["256809072089759745"], "description": "Backers, critics of Egypt president clash in Cairo: Thousands of supporters and opponents of Egypt's new Islamis...  AdF.ly - Suspended"}, "80": {"type": "tweet", "origin": "256809290239725568", "tweets": ["256809290239725568"], "description": "\"We call on everyone in #Tahrir square to pull out\" -- April 6 Youth Movement \u200f\"@shabab6april: \u0646\u0646\u0627\u0634\u062f \u0643\u0644 \u0645\u0646 \u0641\u0649 \u0645\u064a\u062f\u0627\u0646 \u0627\u0644\u062a\u062d\u0631\u064a\u0631 \u0628\u0627\u0644\u0627\u0646\u0633\u062d\u0627\u0628\""}, "81": {"type": "tweet", "origin": "256809491557937153", "tweets": ["256809491557937153"], "description": "Egypt tensions over Morsi spill into clashes "}, "82": {"type": "website", "origin": "http://www.channelnewsasia.com/news", "tweets": ["256809491557937153"], "description": "Egypt tensions over Morsi spill into clashes  Comprehensive news coverage of Asia-Pacific with special reports from Channel NewsAsia's foreign correspondents and regional news sources."}, "83": {"type": "tweet", "origin": "256810040982392833", "tweets": ["256810040982392833"], "description": " Hundreds hospitalised in Tahrir clashes, Brotherhood in hot water: Twin protests in Tahrir... "}, "84": {"type": "website", "origin": "http://english.ahram.org.eg/NewsContent/1/64/55441/Egypt/Politics-/Hundreds-hospitalised-in-Tahrir-clashes,-Brotherho.aspx", "tweets": ["256810040982392833"], "description": " Hundreds hospitalised in Tahrir clashes, Brotherhood in hot water: Twin protests in Tahrir...  \r\n\tHundreds injured in Tahrir clashes, Brotherhood in hot water  - Politics  - Egypt - Ahram Online \r\n"}, "85": {"type": "tweet", "origin": "256810661466750978", "tweets": ["256810661466750978"], "description": "Opponents, supporters of Egypt's president clash in Cairo's Tahrir Square - CTV News: CBC.caOpponen...  #ifollowback"}, "86": {"type": "news", "origin": "http://www.ctvnews.ca/world/opponents-supporters-of-egypt-s-president-clash-in-cairo-s-tahrir-square-1.993394", "tweets": ["256810661466750978"], "description": "Opponents, supporters of Egypt's president clash in Cairo's Tahrir Square - CTV News: CBC.caOpponen...  #ifollowback Thousands of supporters and opponents of Egypt's new Islamist president clashed in Cairo's Tahrir Square on Friday, hurling stones and concrete and swinging sticks at each other in the first such violence since Mohammed Morsi took office more than three months ago."}, "87": {"type": "tweet", "origin": "256812871986606080", "tweets": ["256812871986606080"], "description": "Profile: Who is Mohamed Morsy? "}, "88": {"type": "news", "origin": "http://edition.cnn.com/2012/06/24/world/meast/egypt-morsi-profile/index.html", "tweets": ["256812871986606080"], "description": "Profile: Who is Mohamed Morsy?  Mohamed Morsi, Egypt's first democratically elected president, is a study in contrasts: a strict Islamist educated in the United States."}, "89": {"type": "tweet", "origin": "256814692201279488", "tweets": ["256814692201279488"], "description": "Liberals and Islamists Clash in Tahrir Square:  In the epicenter of the Arab Spring, opponents and supporters of... "}, "90": {"type": "tweet", "origin": "256814998439989248", "tweets": ["256814998439989248"], "description": "Egypt's liberals and Islamists clash, over 100 injured "}, "91": {"type": "tweet", "origin": "256819033469509633", "tweets": ["256819033469509633"], "description": "Egypt's liberals and Islamists clash, over 100 injured "}, "92": {"type": "tweet", "origin": "256819662724145152", "tweets": ["256819662724145152"], "description": "Protest turns violent in Cairo as opponents clash "}, "93": {"type": "tweet", "origin": "256820308579868672", "tweets": ["256820308579868672"], "description": "Violence in Tahrir square today more proof of high stakes in the Egyptian constitutional drafting process. \n"}, "94": {"type": "news", "origin": "https://www.theatlantic.com/international/archive/2012/10/liberals-and-islamists-clash-tahrir-square/322603/", "tweets": ["256820308579868672"], "description": "Violence in Tahrir square today more proof of high stakes in the Egyptian constitutional drafting process. \n In the epicenter of the Arab Spring, opponents and supporters of Egypt&#39;s Muslim Brotherhood are clashing in Tahrir Square today, in the first outbreak of factional violence\u00a0since Islamist President Mohamed Morsi took office.\u00a0"}, "95": {"type": "tweet", "origin": "256821894089687040", "tweets": ["256821894089687040"], "description": "pro #Morsi supporters in #Tahrir today shown their true face of violence and fascist! watch! "}, "96": {"type": "video", "origin": "https://www.youtube.com/watch?v=RCwN8PiMs_g&feature=youtu.be", "tweets": ["256821894089687040"], "description": "pro #Morsi supporters in #Tahrir today shown their true face of violence and fascist! watch!  today pro Morsi and the youth of muslim brotherhood have shown a stream violence against anyone doesn't make a part of them..they have occupied every corner ..."}, "97": {"type": "tweet", "origin": "256824062607781888", "tweets": ["256824062607781888"], "description": "Tahrir Square clashes pit Mohamed Morsi supporters against opponents "}, "98": {"type": "tweet", "origin": "256824133810274304", "tweets": ["256824133810274304"], "description": "via @TheAtlantic Liberals and Islamists Clash in Tahrir Square "}, "99": {"type": "tweet", "origin": "256826281373626368", "tweets": ["256826281373626368"], "description": "Tahrir Square clashes pit Mohamed Morsi supporters against opponents: Dozens of people injured as supporters of ... "}, "100": {"type": "news", "origin": "https://www.theguardian.com/world/2012/oct/12/tahrir-square-clashes-mohamed-morsi", "tweets": ["256826281373626368", "256827036281225218"], "description": "Tahrir Square clashes pit Mohamed Morsi supporters against opponents: Dozens of people injured as supporters of ...  Dozens of people injured as supporters of Egypt's president and Muslim Brotherhood clash with groups protesting against him Tahrir Square clashes pit Mohamed Morsi supporters against opponents - The Guardian "}, "101": {"type": "tweet", "origin": "256826654586970112", "tweets": ["256826654586970112"], "description": "Opponents, supporters of Egypt\u2019s Islamist president clash in Cairo "}, "102": {"type": "news", "origin": "https://www.thestar.com/news/world/2012/10/12/opponents_supporters_of_egypts_islamist_president_clash_in_cairo.html", "tweets": ["256826654586970112"], "description": "Opponents, supporters of Egypt\u2019s Islamist president clash in Cairo  Thousands of supporters and opponents of Egypt\u2019s new Islamist president clashed in Cairo\u2019s Tahrir Square on Friday, hurling stones and concrete and swinging sticks at each other in the first such violence since Mohammed Morsi took office more than three months ago."}, "103": {"type": "tweet", "origin": "256827036281225218", "tweets": ["256827036281225218"], "description": "Tahrir Square clashes pit Mohamed Morsi supporters against opponents - The Guardian "}, "104": {"type": "tweet", "origin": "256832035878993920", "tweets": ["256832035878993920"], "description": "I'm at Tahrir Square (Cairo) w/ 2 others "}, "105": {"type": "website", "origin": "https://www.swarmapp.com/flippo0o0o/checkin/50786917e4b01b4179801334", "tweets": ["256832035878993920"], "description": "I'm at Tahrir Square (Cairo) w/ 2 others  Plaza in \u0627\u0644\u0642\u0627\u0647\u0631\u0629, \u0627\u0644\u0642\u0627\u0647\u0631\u0629"}, "106": {"type": "tweet", "origin": "256834317643313152", "tweets": ["256834317643313152"], "description": "A reminder from @Zeinobia that the MB is lying about the events of Tahrir Square today  #Egypt"}, "107": {"type": "website", "origin": "http://egyptianchronicles.blogspot.fr/2012/10/yo-muslim-brotherhood-muslims-should.html", "tweets": ["256834317643313152"], "description": "A reminder from @Zeinobia that the MB is lying about the events of Tahrir Square today  #Egypt Tahrir , Muslim brotherhood , Protests, Clashes, Morsi"}, "108": {"type": "tweet", "origin": "256837408811802624", "tweets": ["256837408811802624"], "description": "Profile: Who is Mohamed Morsy? "}, "109": {"type": "tweet", "origin": "256841791620395009", "tweets": ["256841791620395009"], "description": "In Pictures: Night Clashes in Tahrir Square "}, "110": {"type": "news", "origin": "http://www.dailynewsegypt.com/2012/10/12/in-pictures-night-clashes-in-tahrir-square/", "tweets": ["256841791620395009"], "description": "In Pictures: Night Clashes in Tahrir Square  Tahrir square, clashes, photo gallery, Morsy, public prosecutor, 100-day plan, Egypt protests - \u00a0 Tahrir square clashes continued on Friday night, between supporters of President\u00a0Mohamed Morsy and protesters criticizng his 100-day plan. Protester"}, "111": {"type": "tweet", "origin": "256843243092860928", "tweets": ["256843243092860928"], "description": "Backers, critics of Egypt president clash in Cairo: Thousands of supporters and opponents of Egypt's new Islamis... "}, "112": {"type": "news", "origin": "https://www.yahoo.com/news/backers-critics-egypt-president-clash-cairo-164003350.html", "tweets": ["256843243092860928"], "description": "Backers, critics of Egypt president clash in Cairo: Thousands of supporters and opponents of Egypt's new Islamis...  Thousands of supporters and opponents of Egypt's new Islamist president clashed in Cairo's Tahrir Square on Friday in the first such violence since Mohammed Morsi took office more than three months ago, as liberal and secular activists erupted with anger accusing the Muslim Brotherhood of trying"}, "113": {"type": "tweet", "origin": "256844178137444353", "tweets": ["256844178137444353"], "description": "\"@SherineT: Fight breaking out in #Tahrir between those pro and anti #morsi "}, "114": {"type": "img_upload", "origin": "http://pbs.twimg.com/media/A4_6rk8CQAAqtLE.jpg", "tweets": ["256844178137444353"], "description": "\"@SherineT: Fight breaking out in #Tahrir between those pro and anti #morsi "}, "115": {"type": "tweet", "origin": "256846808251265024", "tweets": ["256846808251265024"], "description": "Opponents, supporters of Egypt's Islamist president clash in Cairo's Tahrir Square - Washington Post "}, "116": {"type": "tweet", "origin": "256852000812183552", "tweets": ["256852000812183552"], "description": "Video: MB (Supporters and/or Members) heckle and wreck opposition stage in #Tahrir today, chant \"Morsi! Morsi!\" "}, "117": {"type": "video", "origin": "https://www.youtube.com/watch?v=TZLumVyrBcs", "tweets": ["256852000812183552"], "description": "Video: MB (Supporters and/or Members) heckle and wreck opposition stage in #Tahrir today, chant \"Morsi! Morsi!\"  \u0647\u062c\u0648\u0645 \u0627\u0644\u0627\u062e\u0648\u0627\u0646 \u0639\u0644\u0649 \u0627\u0644\u0645\u0646\u0635\u0629 \u0648\u062a\u0643\u0633\u064a\u0631\u0647\u0627 \u0628\u0639\u062f \u0635\u0644\u0627\u0629 \u0627\u0644\u062c\u0645\u0639\u0629 \u0641\u0649 \u0645\u064a\u062f\u0627\u0646 \u0627\u0644\u062a\u062d\u0631\u064a\u0631 https://www.facebook.com/elt7rirt7rirna2011 \u0627\u0644\u062a\u062d\u0631\u064a\u0631 \u062a\u062d\u0631\u064a\u0631\u0646\u0627 \u0648 \u0627\u0644\u0645\u064a\u062f\u0627\u0646 \u0645\u064a\u062f\u0627\u0646\u0627 https://www.fa..."}, "118": {"type": "tweet", "origin": "256857814134304768", "tweets": ["256857814134304768"], "description": "Egypt has tensions clashes in Cairo's Tahrir Square and Mursi don't calm down - Egyptians loves clashes than \u2026 "}, "119": {"type": "website", "origin": "http://hcworldservice.tumblr.com/post/33447772804/egypt-has-tensions-clashes-in-cairos-tahrir#_=_", "tweets": ["256857814134304768"], "description": "Egypt has tensions clashes in Cairo's Tahrir Square and Mursi don't calm down - Egyptians loves clashes than \u2026  Egyptians loves clashes than peace. Today, opponents and supporters of president Mohammed Mursi has broken out in Tahrir Square over against 24 people are acquitted of claims to attacks protests on..."}, "120": {"type": "tweet", "origin": "256862394091970560", "tweets": ["256862394091970560"], "description": "Tahrir Square, Egypt....lol tell me again how EVERYONE in Egypt likes Morsi. My ass they do "}, "121": {"type": "img_upload", "origin": "http://pbs.twimg.com/media/A5CO_IxCIAELtpP.jpg", "tweets": ["256862394091970560"], "description": "Tahrir Square, Egypt....lol tell me again how EVERYONE in Egypt likes Morsi. My ass they do "}, "122": {"type": "tweet", "origin": "256862545313415168", "tweets": ["256862545313415168"], "description": "Pro- and anti-Mursi protesters clash in Egypt\u2019s iconic Tahrir square  ~ VIA @AlArabiya_Eng"}, "123": {"type": "tweet", "origin": "256862952215420928", "tweets": ["256862952215420928"], "description": "Morsi Supporters, Opponents Clash in Cairo - Voice of America: Voice of AmericaMorsi Supporters, Opponents Clash... "}, "124": {"type": "news", "origin": "http://www.voanews.com/a/supporters-opponents-of-egypt-president-morsi-clash-in-cairo/1525560.html", "tweets": ["256862952215420928", "256862956132913153"], "description": "Morsi Supporters, Opponents Clash in Cairo - Voice of America: Voice of AmericaMorsi Supporters, Opponents Clash...  Liberal, leftist groups called Friday's protest to demand more action from Morsi after his first 100 days in office Morsi Supporters, Opponents Clash in Cairo - Voice of America: Voice of AmericaMorsi Supporters, Opponents Clash... "}, "125": {"type": "tweet", "origin": "256862956132913153", "tweets": ["256862956132913153"], "description": "Morsi Supporters, Opponents Clash in Cairo - Voice of America: Voice of AmericaMorsi Supporters, Opponents Clash... "}, "126": {"type": "tweet", "origin": "256863526705065985", "tweets": ["256863526705065985"], "description": "Mohamed Morsy doesn't deserve vocal cords."}, "127": {"type": "tweet", "origin": "256866504652496896", "tweets": ["256866504652496896"], "description": "Man attacked in #Tahrir during violent clashes between pro and anti gov groups - more on  #Egypt "}, "128": {"type": "img_upload", "origin": "http://pbs.twimg.com/media/A5CSuZzCIAAsFSz.jpg", "tweets": ["256866504652496896"], "description": "Man attacked in #Tahrir during violent clashes between pro and anti gov groups - more on  #Egypt "}, "129": {"type": "website", "origin": "http://polarisimages.com/", "tweets": ["256866504652496896"], "description": "Man attacked in #Tahrir during violent clashes between pro and anti gov groups - more on  #Egypt  Polaris Images represents photographers and distributes photographs to media industries worldwide. Founded by JP Pappis in 2002 in New York."}, "130": {"type": "tweet", "origin": "256866508775497728", "tweets": ["256866508775497728"], "description": "Egypt's liberals, Islamists clash, 110 reported injured"}, "131": {"type": "tweet", "origin": "256867418775908353", "tweets": ["256867418775908353"], "description": "110 Egyptians injured in clashes at Cairo's Tahrir Square - Xinhua "}, "132": {"type": "website", "origin": "http://news.xinhuanet.com/english/world/2012-10/13/c_123817545.htm", "tweets": ["256867418775908353"], "description": "110 Egyptians injured in clashes at Cairo's Tahrir Square - Xinhua  \r\n110 Egyptians injured in clashes at Cairo's Tahrir Square - Xinhua | English.news.cn\r\n"}, "133": {"type": "tweet", "origin": "256870397117612033", "tweets": ["256870397117612033"], "description": "In Pictures: Protesters clash in Tahrir Square - Daily News Egypt "}, "134": {"type": "tweet", "origin": "256880400301961216", "tweets": ["256880400301961216"], "description": "Egypt: Clashes In Cairo\u2019s Tahrir Square "}, "135": {"type": "news", "origin": "http://www.eurasiareview.com/12102012-egypt-clashes-in-cairos-tahrir-square/", "tweets": ["256880400301961216"], "description": "Egypt: Clashes In Cairo\u2019s Tahrir Square  Supporters and opponents of Egyptian President Mohamed Morsi clashed Friday after separately demonstrating in Tahrir Square in central Cairo, amid standoff between the executive and the judiciary. \u2026"}, "136": {"type": "tweet", "origin": "256880874098946048", "tweets": ["256880874098946048"], "description": "VIDEO: Egypt tensions spark clashes: In Egypt, more than 100 people have been hurt in clashes between supporters... "}, "137": {"type": "website", "origin": "http://www.bbc.co.uk/news/world-middle-east-19931091#sa-ns_mchannel=rss&ns_source=PublicRSS20-sa", "tweets": ["256880874098946048", "256880891232653312", "256880983452831745", "256881864143417344", "256883936284786689", "256883940537794560", "256885257415045121"], "description": "VIDEO: Egypt tensions spark clashes: In Egypt, more than 100 people have been hurt in clashes between supporters...  In Egypt, more than 100 people have been hurt in clashes between supporters of President Mursi and opponents in Cairo. VIDEO: Egypt tensions spark clashes: In Egypt, more than 100 people have been hurt in clashes between supporters...  VIDEO: Egypt tensions spark clashes: In Egypt, more than 100 people have been hurt in clashes between supporters...  VIDEO: Egypt tensions spark clashes: In Egypt, more than 100 people have been hurt in clashes between supporters...  VIDEO: Egypt tensions spark clashes: In Egypt, more than 100 people have been hurt in clashes between supporters...  VIDEO: Egypt tensions spark clashes: In Egypt, more than 100 people have been hurt in clashes between supporters...  VIDEO: Egypt tensions spark clashes: In Egypt, more than 100 people have been hurt in clashes between supporters... "}, "138": {"type": "tweet", "origin": "256880891232653312", "tweets": ["256880891232653312"], "description": "VIDEO: Egypt tensions spark clashes: In Egypt, more than 100 people have been hurt in clashes between supporters... "}, "139": {"type": "tweet", "origin": "256880983452831745", "tweets": ["256880983452831745"], "description": "VIDEO: Egypt tensions spark clashes: In Egypt, more than 100 people have been hurt in clashes between supporters... "}, "140": {"type": "tweet", "origin": "256881864143417344", "tweets": ["256881864143417344"], "description": "VIDEO: Egypt tensions spark clashes: In Egypt, more than 100 people have been hurt in clashes between supporters... "}, "141": {"type": "tweet", "origin": "256883621531635712", "tweets": ["256883621531635712"], "description": "Supporters and Opponents of Egypt's Morsi Protest in Cairo's Tahrir Square "}, "142": {"type": "tweet", "origin": "256883936284786689", "tweets": ["256883936284786689"], "description": "VIDEO: Egypt tensions spark clashes: In Egypt, more than 100 people have been hurt in clashes between supporters... "}, "143": {"type": "tweet", "origin": "256883940537794560", "tweets": ["256883940537794560"], "description": "VIDEO: Egypt tensions spark clashes: In Egypt, more than 100 people have been hurt in clashes between supporters... "}, "144": {"type": "tweet", "origin": "256885257415045121", "tweets": ["256885257415045121"], "description": "VIDEO: Egypt tensions spark clashes: In Egypt, more than 100 people have been hurt in clashes between supporters... "}, "145": {"type": "tweet", "origin": "256886729749979136", "tweets": ["256886729749979136"], "description": "After the events today in Tahrir ana Flol wesh,hate u Morsy."}, "146": {"type": "tweet", "origin": "256893595548807169", "tweets": ["256893595548807169"], "description": "Egypt tensions over Morsi spill into clashes - Livemint "}, "147": {"type": "tweet", "origin": "256895789429837824", "tweets": ["256895789429837824"], "description": "VIDEO: Egypt tensions spark clashes: In Egypt, more than 100 people have been hurt in clashes between supporters... "}, "148": {"type": "website", "origin": "http://adf.ly/DdeSh", "tweets": ["256895789429837824"], "description": "VIDEO: Egypt tensions spark clashes: In Egypt, more than 100 people have been hurt in clashes between supporters...  AdF.ly"}, "149": {"type": "tweet", "origin": "256899572452954112", "tweets": ["256899572452954112"], "description": "Clashes in Cairo Tahrir square "}, "150": {"type": "tweet", "origin": "256899593411895297", "tweets": ["256899593411895297"], "description": "Morsi\u2019s supporters, opposition clash in Cairo "}, "151": {"type": "tweet", "origin": "256899601993453569", "tweets": ["256899601993453569"], "description": "Update: More protesters injured as fighting intensifies in Tahrir "}, "152": {"type": "tweet", "origin": "256900193432256512", "tweets": ["256900193432256512"], "description": "Egypt tensions over Morsi spill into clashes: CAIRO: Supporters of President Mohamed Morsi clashed with opponent... "}, "153": {"type": "news", "origin": "http://www.freemalaysiatoday.com/category/world/2012/10/13/egypt-tensions-over-morsi-spill-into-clashes/", "tweets": ["256900193432256512"], "description": "Egypt tensions over Morsi spill into clashes: CAIRO: Supporters of President Mohamed Morsi clashed with opponent...  CAIRO: Supporters of President Mohamed Morsi clashed with opponents in Cairo's Tahrir Square yesterday in the worst violence over Egypt's new Islamist leader, a day after he crossed swords with the judiciary.\r\n\r\n\r\nMorsi's Muslim Brotherhood movement and a coalition of secular leaning"}, "154": {"type": "tweet", "origin": "256901946370293760", "tweets": ["256901946370293760"], "description": "Protesters Clash in Tahrir Square | Common Dreams #WorWat "}, "155": {"type": "news", "origin": "http://www.commondreams.org/news/2012/10/12/protesters-clash-tahrir-square", "tweets": ["256901946370293760"], "description": "Protesters Clash in Tahrir Square | Common Dreams #WorWat  Egypt's Muslim Brotherhood party is urging its supporters to leave Tahrir Square, after fighting took place there between rival groups. More than 100 people have been injured in clashes between protesters who back President Mohamed Morsi and those who oppose him. It is the worst violence under the Morsi presidency. Al Jazeera's Sherine Tadros reports from Cairo."}, "156": {"type": "tweet", "origin": "256915825364193280", "tweets": ["256915825364193280"], "description": "Islamists, Secularists Clash in Cairo  ~Sad this is in Tahrir Square"}, "157": {"type": "news", "origin": "https://www.wsj.com/articles/SB10000872396390444657804578052590265855944", "tweets": ["256915825364193280"], "description": "Islamists, Secularists Clash in Cairo  ~Sad this is in Tahrir Square Dozens were injured in clashes between secular-leaning and Islamist activists in the heart of Egypt's capital in the first such internecine political violence since the country's Muslim Brotherhood-backed president took office in late June."}, "158": {"type": "tweet", "origin": "256918044402655232", "tweets": ["256918044402655232"], "description": "Opponents and Supporters of Egypt's President Clash - New York Times: New York TimesOpponents and Supporters of ... "}, "159": {"type": "news", "origin": "http://www.nytimes.com/2012/10/13/world/middleeast/mohamed-morsis-critics-and-backers-clash-in-cairos-tahrir-square.html", "tweets": ["256918044402655232", "256918048215285761", "256980648391241728"], "description": "Opponents and Supporters of Egypt's President Clash - New York Times: New York TimesOpponents and Supporters of ...  At least 110 people were injured in the bloodiest clashes between the two sides of Egypt\u2019s main ideological divide since the start of the revolt that toppled President Hosni Mubarak. Opponents and Supporters of Egypt's President Clash - New York Times  Opponents and Supporters of Morsi, Egypt\u2019s President, Clash in Tahrir Square "}, "160": {"type": "tweet", "origin": "256918048215285761", "tweets": ["256918048215285761"], "description": "Opponents and Supporters of Egypt's President Clash - New York Times "}, "161": {"type": "tweet", "origin": "256919822540087296", "tweets": ["256919822540087296"], "description": "VIDEO: Clashes in Tahrir on Friday of accountability  via @ahramonline"}, "162": {"type": "website", "origin": "http://english.ahram.org.eg/NewsContentMulti/55468/Multimedia.aspx", "tweets": ["256919822540087296", "257016560093388800"], "description": "VIDEO: Clashes in Tahrir on Friday of accountability  via @ahramonline \r\n\tVIDEO: Clashes in Egypt's Tahrir on 'Friday of accountability' - Multimedia - Ahram Online \r\n Clashes in #Egypt  \u2026 via @bravo4egypt #Tahrir"}, "163": {"type": "tweet", "origin": "256919961061167104", "tweets": ["256919961061167104"], "description": "\"@blakehounshell 100 ppl  injured after clashes breakout during rival rallies in Cairo's Tahrir Square Friday prayers "}, "164": {"type": "website", "origin": "http://www.aljazeera.com/news/middleeast/2012/10/20121012133639244689.html", "tweets": ["256919961061167104"], "description": "\"@blakehounshell 100 ppl  injured after clashes breakout during rival rallies in Cairo's Tahrir Square Friday prayers  At least 100 people injured after clashes erupt during rival rallies in Cairo's Tahrir Square after Friday prayers."}, "165": {"type": "tweet", "origin": "256924012838526976", "tweets": ["256924012838526976"], "description": "Mohamed Morsi\u2019s Critics and Backers Clash in Cairo\u2019s Tahrir Square (New York Times): Share With Friends:  |  | T... "}, "166": {"type": "website", "origin": "http://adf.ly/DdkHE", "tweets": ["256924012838526976"], "description": "Mohamed Morsi\u2019s Critics and Backers Clash in Cairo\u2019s Tahrir Square (New York Times): Share With Friends:  |  | T...  AdF.ly"}, "167": {"type": "tweet", "origin": "256924339818074112", "tweets": ["256924339818074112"], "description": "More than 100 injured as protesters clash in Egypt "}, "168": {"type": "tweet", "origin": "256925501883555840", "tweets": ["256925501883555840"], "description": "Mayhem In Tahrir: Clashes Erupt Between Supporters And Opponents Of Morsi And The Brotherhood - "}, "169": {"type": "tweet", "origin": "256928328588599296", "tweets": ["256928328588599296"], "description": "Scores injured as rival protests clash over Morsi in Cairo\u2019s Tahrir Square: Protesters throw stones after scuffl... "}, "170": {"type": "news", "origin": "http://www.bignewsnetwork.com/article/210008337/scores-injured-as-rival-protests-clash-over-morsi-in-cairos-tahrir-square", "tweets": ["256928328588599296"], "description": "Scores injured as rival protests clash over Morsi in Cairo\u2019s Tahrir Square: Protesters throw stones after scuffl...  Scores injured as rival protests clash over Morsi in Cairos Tahrir Square"}, "171": {"type": "tweet", "origin": "256929763191554048", "tweets": ["256929763191554048"], "description": "Scores injured as rival protests clash over Morsi in Cairo&amp;amp;#x2019;s Tahrir Square "}, "172": {"type": "tweet", "origin": "256936859903614977", "tweets": ["256936859903614977"], "description": "The Jawa Report: Egypt: Tahrir Square Protests, Again "}, "173": {"type": "website", "origin": "http://mypetjawa.mu.nu/archives/213877.php", "tweets": ["256936859903614977"], "description": "The Jawa Report: Egypt: Tahrir Square Protests, Again  The Jawa Report: Egypt: Tahrir Square Protests, Again"}, "174": {"type": "tweet", "origin": "256943046296485888", "tweets": ["256943046296485888"], "description": "#DesiCommunity.org 110 Egyptians injured in clashes at Cairo's Tahrir Square "}, "175": {"type": "tweet", "origin": "256949140712464384", "tweets": ["256949140712464384"], "description": "#Egypt #Jan25 VIDEO: Clashes in Egypt\u2019s Tahrir on \u2018Friday of accountability\u2019  #tahrir"}, "176": {"type": "tweet", "origin": "256967650461249536", "tweets": ["256967650461249536"], "description": "Clashes between rival groups in Tahrir Square "}, "177": {"type": "website", "origin": "http://wargamarhaen.blogspot.fr/2012/10/clashes-between-rival-groups-in-tahrir.html", "tweets": ["256967650461249536"], "description": "Clashes between rival groups in Tahrir Square  BERITA DARI SUMBER SEMASA DAN TERKINI - HUBUNGI KAMI DI wargamarhaen@gmail.com\n"}, "178": {"type": "tweet", "origin": "256980648391241728", "tweets": ["256980648391241728"], "description": "Opponents and Supporters of Morsi, Egypt\u2019s President, Clash in Tahrir Square "}, "179": {"type": "tweet", "origin": "256994615452893184", "tweets": ["256994615452893184"], "description": "PAKIS RAPE KIDS: 110 injured in clashes at Cairo's Tahrir Square: Clashes erupted Friday at T...  #oldham #middleton"}, "180": {"type": "website", "origin": "http://www.chinadaily.com.cn/world/2012-10/13/content_15815170.htm", "tweets": ["256994615452893184"], "description": "PAKIS RAPE KIDS: 110 injured in clashes at Cairo's Tahrir Square: Clashes erupted Friday at T...  #oldham #middleton Clashes erupted Friday at Tahrir Square, a downtown area in Egypt's capital Cairo, leaving 110 people injured, the health ministry reported."}, "181": {"type": "tweet", "origin": "256994695140478978", "tweets": ["256994695140478978"], "description": "Clashes erupt on Egypt\u2019s Tahrir Square, over 100 injured "}, "182": {"type": "tweet", "origin": "256995684820058113", "tweets": ["256995684820058113"], "description": "AK wants 2 do 2 India, what Tehrir Square did to Egypt! Shameful !! ----&gt; \"@ArvindKejriwal7: Parl police stn - next tahrir square.\""}, "183": {"type": "tweet", "origin": "257003318805688320", "tweets": ["257003318805688320"], "description": "Rival protesters clash in Egypt's capital: At least 100 people injured after clashes erupt during rival rallies ... "}, "184": {"type": "tweet", "origin": "257007609339576320", "tweets": ["257007609339576320"], "description": "Pro-Brotherhood demonstrators attack 'Accountability Friday' protest in Tahrir Square, destroy platform   #news"}, "185": {"type": "website", "origin": "http://english.ahram.org.eg/News/55417.aspx", "tweets": ["257007609339576320"], "description": "Pro-Brotherhood demonstrators attack 'Accountability Friday' protest in Tahrir Square, destroy platform   #news \r\n\tPro-Brotherhood demonstrators attack 'Accountability Friday' protest in Tahrir - Politics  - Egypt - Ahram Online \r\n"}, "186": {"type": "tweet", "origin": "257011124015349760", "tweets": ["257011124015349760"], "description": "Demonstrations Return to Tahrir Square Due to Outrage Over Acquittal in Camel Battle: Hundreds of protesters sta... "}, "187": {"type": "news", "origin": "http://www.bignewsnetwork.com/article/210013768/demonstrations-return-to-tahrir-square-due-to-outrage-over-acquittal-in-camel-battle", "tweets": ["257011124015349760"], "description": "Demonstrations Return to Tahrir Square Due to Outrage Over Acquittal in Camel Battle: Hundreds of protesters sta...  Demonstrations Return to Tahrir Square Due to Outrage Over Acquittal in Camel Battle"}, "188": {"type": "tweet", "origin": "257016560093388800", "tweets": ["257016560093388800"], "description": "Clashes in #Egypt  \u2026 via @bravo4egypt #Tahrir"}, "189": {"type": "tweet", "origin": "257017943953645568", "tweets": ["257017943953645568"], "description": "110 Egyptians injured in clashes at Cairo's Tahrir Square "}, "190": {"type": "news", "origin": "https://in.news.yahoo.com/110-egyptians-injured-clashes-cairos-tahrir-square-065753385.html", "tweets": ["257017943953645568"], "description": "110 Egyptians injured in clashes at Cairo's Tahrir Square  Cairo, Oct. 13 (Xinhua-ANI): Clashes erupted Friday at Tahrir Square, a downtown area in Egypt's capital Cairo, leaving 110 people injured, the health ministry reported."}, "191": {"type": "tweet", "origin": "257032444073611265", "tweets": ["257032444073611265"], "description": "The Egyptian museum was not impacted by clashes in Tahrir, says minister  #Egypt"}, "192": {"type": "website", "origin": "http://english.ahram.org.eg/NewsContent/1/64/55463/Egypt/Politics-/The-Egyptian-museum-was-not-impacted-by-clashes-in.aspx", "tweets": ["257032444073611265"], "description": "The Egyptian museum was not impacted by clashes in Tahrir, says minister  #Egypt \r\n\tEgyptian Museum untouched by Tahrir clashes, says minister - Ancient Egypt - Heritage - Ahram Online \r\n"}, "193": {"type": "tweet", "origin": "257042745028382720", "tweets": ["257042745028382720"], "description": "Injuries yesterday after clashes broke out between pro and anti-brotherhood protesters #tahrir "}, "194": {"type": "website", "origin": "https://imageshack.com/lost/g0h0dedj", "tweets": ["257042745028382720"], "description": "Injuries yesterday after clashes broke out between pro and anti-brotherhood protesters #tahrir  Unlimited space to host images, easy to use image uploader, albums, photo hosting, sharing, dynamic image resizing on web and mobile."}, "195": {"type": "tweet", "origin": "257055180984565760", "tweets": ["257055180984565760"], "description": "#Tahrir clashes on Friday .. Via #BBC Arabic #Cairo bureau "}, "196": {"type": "img_upload", "origin": "http://pbs.twimg.com/media/A5E-Uz6CQAAMU3U.jpg", "tweets": ["257055180984565760"], "description": "#Tahrir clashes on Friday .. Via #BBC Arabic #Cairo bureau "}, "197": {"type": "tweet", "origin": "257059560148328448", "tweets": ["257059560148328448"], "description": "Pro- and anti-Mursi protesters clash in Egypt\u2019s iconic Tahrir square -  #Islam #Muslims #Egypt"}, "198": {"type": "website", "origin": "http://en.ammonnews.net/article.aspx", "tweets": ["257059560148328448"], "description": "Pro- and anti-Mursi protesters clash in Egypt\u2019s iconic Tahrir square -  #Islam #Muslims #Egypt AMMONNEWS-Clashes erupted in Cairo\u2019s Tahrir Square Friday as supporters and opponents of Egyptian President Mohammed Mursi tried to wrest control of t,Clashes /erupted /Cairo/ Tahrir Square/supporters/ opponents /Egyptian President /Mohammed Mursi/iconic square/rival rallies/ AFP/\r\n"}, "199": {"type": "tweet", "origin": "257060155785613312", "tweets": ["257060155785613312"], "description": "At least 110 injured as Morsi supporters,opponents clash at Tahrir Square: Clashes erupted in Cairo's Tahrir Squ... "}, "200": {"type": "tweet", "origin": "257062332495175681", "tweets": ["257062332495175681"], "description": "Egypt's liberals, Islamists clash, 110 reported injured "}, "201": {"type": "website", "origin": "http://af.reuters.com/article/topNews/idAFJOE89C00M20121013", "tweets": ["257062332495175681"], "description": "Egypt's liberals, Islamists clash, 110 reported injured  CAIRO (Reuters) - Opponents and supporters of Egyptian President Mohamed Mursi clashed in Cairo on Friday in the first street violence between rival factions since the Islamist leader took office.\nIslamists"}, "202": {"type": "tweet", "origin": "257065847422599168", "tweets": ["257065847422599168"], "description": "\u201c@MENewsflash: #Egyptian Museum not touched by Tahrir clashes, says minister  Morsi needs to protect past."}, "203": {"type": "tweet", "origin": "257070561816113153", "tweets": ["257070561816113153"], "description": "Camps for, against Egypt president clash in Cairo - Yahoo! News  #TAHRIR"}, "204": {"type": "news", "origin": "https://www.yahoo.com/news/camps-against-egypt-president-clash-cairo-144001147.html", "tweets": ["257070561816113153"], "description": "Camps for, against Egypt president clash in Cairo - Yahoo! News  #TAHRIR For the first time since Egypt's new Islamist president took office, his supporters clashed with liberal and leftist protesters in Cairo, storming a stage erected by the opposition activists, smashing loudspeakers and tearing the structure down during competing rallies Friday."}, "205": {"type": "tweet", "origin": "257071769645637633", "tweets": ["257071769645637633"], "description": "Smoke rises from Tahrir Sq Clashes "}, "206": {"type": "website", "origin": "https://www.flickr.com/photos/zarwan/8080218388/", "tweets": ["257071769645637633"], "description": "Smoke rises from Tahrir Sq Clashes  Btwn Brotherhood supporters and detractors. At least 110 people were injured."}, "207": {"type": "tweet", "origin": "257075716301131776", "tweets": ["257075716301131776"], "description": "#Egypt #Jan25 Egyptian Museum not touched by Tahrir clashes, says minister  #tahrir"}, "208": {"type": "tweet", "origin": "257099917489745920", "tweets": ["257099917489745920"], "description": "This seems a bit squeamish: Tahrir clashes caused flight cancellations "}, "209": {"type": "news", "origin": "http://www.egyptindependent.com/news/airport-sources-tahrir-clashes-caused-flight-cancellations", "tweets": ["257099917489745920"], "description": "This seems a bit squeamish: Tahrir clashes caused flight cancellations  \u00a0 Air traffic to Egypt has been affected by the clashes in Tahrir Square Friday, with several airlines canceling flights due to economic infeasibility, according to a source at Cairo International Airport."}, "210": {"type": "tweet", "origin": "257107572425895936", "tweets": ["257107572425895936"], "description": "Freedom and Justice Party Statement Condemning #Tahrir Square Friday Clashes - #FJP #Egypt "}, "211": {"type": "tweet", "origin": "257130297181753345", "tweets": ["257130297181753345"], "description": "Egyptian Museum untouched by Tahrir clashes, says minister  #Egypt"}, "212": {"type": "tweet", "origin": "257148722360750081", "tweets": ["257148722360750081"], "description": "Egypt's President Keeps Mahmoud as Prosecutor General: Egyptian President Mohamed Morsi has agreed to keep Egypt... "}, "213": {"type": "news", "origin": "http://www.voanews.com/a/egypt-president-keeps-mahmoud-as-prosecutor-general/1526018.html", "tweets": ["257148722360750081"], "description": "Egypt's President Keeps Mahmoud as Prosecutor General: Egyptian President Mohamed Morsi has agreed to keep Egypt...  Morsi had removed Mahmoud from office after court acquitted loyalists of ousted President Mubarak on charges of organizing brutal attack against protesters"}, "214": {"type": "tweet", "origin": "257150043562328064", "tweets": ["257150043562328064"], "description": "World News : Egypt's President Keeps Mahmoud as Prosecutor General: Egyptian President Mohamed Morsi has agreed ... "}, "215": {"type": "website", "origin": "http://adf.ly/DekHt", "tweets": ["257150043562328064"], "description": "World News : Egypt's President Keeps Mahmoud as Prosecutor General: Egyptian President Mohamed Morsi has agreed ...  AdF.ly"}, "216": {"type": "tweet", "origin": "257150912148160513", "tweets": ["257150912148160513"], "description": "Tahrir Square reopened after protests: CAIRO, Oct. 13 (UPI) --  Traffic in Tahrir Square in Cairo was back to no... "}, "217": {"type": "tweet", "origin": "257151893434929152", "tweets": ["257151893434929152"], "description": "Revolutionary Khaled Said Page blasts Brotherhood version of #Tahrir clashes "}, "218": {"type": "website", "origin": "http://english.ahram.org.eg/News/55480.aspx", "tweets": ["257151893434929152"], "description": "Revolutionary Khaled Said Page blasts Brotherhood version of #Tahrir clashes  \r\n\tRevolutionary 'Khaled Said' page blasts Brotherhood version of Tahrir clashes - Politics  - Egypt - Ahram Online \r\n"}, "219": {"type": "tweet", "origin": "257153680309100544", "tweets": ["257153680309100544"], "description": "#Egypt #Masr Egyptian museum was not impacted by clashes in Tahrir: Minister  #Sinai"}, "220": {"type": "tweet", "origin": "257160692984066048", "tweets": ["257160692984066048"], "description": "A supporter of Egypt's President Mohamed Mursi punches an anti-Brotherhood at Tahrir Square - Mohamed Abd El Ghany "}, "221": {"type": "img_upload", "origin": "http://pbs.twimg.com/media/A5GeSawCMAAScLz.jpg", "tweets": ["257160692984066048"], "description": "A supporter of Egypt's President Mohamed Mursi punches an anti-Brotherhood at Tahrir Square - Mohamed Abd El Ghany "}, "222": {"type": "tweet", "origin": "257161410130350080", "tweets": ["257161410130350080"], "description": "India News Parliament Street will be the next Tahrir Square, Arvind Kejriwal tells crowd "}, "223": {"type": "news", "origin": "http://www.indiatvnews.com/politics/national/parliament-street-will-be-the-next-tahrir-square-arvind-kejriwal-6448.html", "tweets": ["257161410130350080"], "description": "India News Parliament Street will be the next Tahrir Square, Arvind Kejriwal tells crowd  New Delhi, Oct\u00a0 13: The war of attrition between Arvind Kejriwal and Salman Khurshid over allegations of irregularities against the Law Minister's NGO escalated"}, "224": {"type": "tweet", "origin": "257181735735930880", "tweets": ["257181735735930880"], "description": "More than 100 injured as protesters clash in Egypt | The Raw Story "}, "225": {"type": "tweet", "origin": "257239672009396224", "tweets": ["257239672009396224"], "description": "Protestors Clash In Tahrir Square:  -- BG32"}, "226": {"type": "news", "origin": "http://www.breitbart.com/video/2012/10/13/protestors-clash-in-tahrir-square/", "tweets": ["257239672009396224"], "description": "Protestors Clash In Tahrir Square:  -- BG32 Critics and supporters of Egyptian President Morsy clash after his first 100 days in office."}, "227": {"type": "tweet", "origin": "257253651427508224", "tweets": ["257253651427508224"], "description": "#Photography #EgyPhoto Clashes Erupted in Tahrir  (By @IbnGamalDin)"}, "228": {"type": "website", "origin": "https://www.flickr.com/photos/mahmoudgamaldin/8083269180/", "tweets": ["257253651427508224"], "description": "#Photography #EgyPhoto Clashes Erupted in Tahrir  (By @IbnGamalDin) About 20 liberal and leftist groups called for a protest on Friday #Oct12 demanding a new Constituent Assembly that represents all Egyptians, on the other hand the Muslim Brotherhood called for a simultaneous protest in Tahrir Square to condemn the Camel Battle Verdict.  Clashes erupted between liberal & leftist protesters and pro-Morsi, after MB supporters destroyed the stage of the liberal and leftist."}}